bt_python_sdk-1.0.1.dist-info/licenses/LICENSE
examples/__init__.py
examples/system_status.py
examples/website_advanced.py
examples/website_backup.py
examples/website_basic.py
pybt/__init__.py
pybt/__version__.py
pybt/api/__init__.py
pybt/api/system.py
pybt/api/website.py
pybt/core/__init__.py
pybt/core/client.py
pybt/core/config.py
pybt/core/token.py
bt_python_sdk-1.0.1.dist-info/METADATA
bt_python_sdk-1.0.1.dist-info/WHEEL
bt_python_sdk-1.0.1.dist-info/top_level.txt
bt_python_sdk-1.0.1.dist-info/RECORD
