Metadata-Version: 2.4
Name: bt-python-sdk
Version: 1.0.1
Summary: Pybt is a Python SDK for the BT Panel API. It provides a comprehensive set of tools for managing and automating tasks on servers running the BaoTa Panel.
Home-page: https://github.com/adamzhang1987/bt-python-sdk
Author: Adam Zhang
Author-email: Adam Zhang <adamzhang1987@gmail.com>
License-Expression: MIT
Project-URL: Homepage, https://github.com/adamzhang1987/bt-python-sdk
Project-URL: Issues, https://github.com/adamzhang1987/bt-python-sdk/issues
Classifier: Programming Language :: Python :: 3
Classifier: Operating System :: OS Independent
Requires-Python: >=3.8
License-File: LICENSE
Requires-Dist: python-dotenv>=1.1.0
Requires-Dist: requests>=2.32.3
Dynamic: author
Dynamic: home-page
Dynamic: license-file
Dynamic: requires-python
